pptcom/__init__.py
pptcom/files.py
pptcom-0.1.dist-info/DESCRIPTION.rst
pptcom-0.1.dist-info/METADATA
pptcom-0.1.dist-info/RECORD
pptcom-0.1.dist-info/WHEEL
pptcom-0.1.dist-info/metadata.json
pptcom-0.1.dist-info/top_level.txt
