Metadata-Version: 2.0
Name: pptcom
Version: 0.1
Summary: Use Microsoft PowerPoint within Python with the help of COM
Home-page: https://github.com/m-rossi/pptcom
Author: Marco Rossi
Author-email: developer@marco-rossi.com
License: MIT
Requires-Dist: comtypes
Provides-Extra: test
Requires-Dist: pytest; extra == 'test'
Requires-Dist: python-pptx; extra == 'test'
